CHANGES.txt
LICENCE.txt
MANIFEST.in
README.rst
requirements.txt
setup.py
djangoutillib/__init__.py
djangoutillib/models.py
djangoutillib/settings.py
djangoutillib/tests.py
djangoutillib/urls.py
djangoutillib/utils.py
djangoutillib/wsgi.py
djangoutillib.egg-info/PKG-INFO
djangoutillib.egg-info/SOURCES.txt
djangoutillib.egg-info/dependency_links.txt
djangoutillib.egg-info/requires.txt
djangoutillib.egg-info/top_level.txt