Metadata-Version: 1.0
Name: djangoutillib
Version: 0.1.0
Summary: Collection of generic django utilities
Home-page: http://github.com/EdwinvO/djangoutillib
Author: Edwin van Opstal
Author-email: evo.se-technology.com
License: LICENSE.txt
Platform: UNKNOWN
